macro_parser/__init__.py
macro_parser/config.py
macro_parser/models.py
macro_parser/utils.py
macro_parser-0.3.1.dist-info/LICENSE
macro_parser-0.3.1.dist-info/METADATA
macro_parser-0.3.1.dist-info/WHEEL
macro_parser-0.3.1.dist-info/top_level.txt
macro_parser-0.3.1.dist-info/RECORD
